PCGCPP.cpython-310-darwin.so
pcg-cpp/include/pcg_extras.hpp
pcg-cpp/include/pcg_random.hpp
pcg-cpp/include/pcg_uint128.hpp
py_pcg/PCGCPP.pyi
py_pcg/__init__.py
py_pcg/__init__.pyi
py_pcg/normal_cdf.cpp
py_pcg/normal_cdf.hpp
py_pcg/pcg32.py
py_pcg/pcg32.pyi
py_pcg/pcg_wrapper.cpp
Python_PCG-0.2.dist-info/LICENSE
Python_PCG-0.2.dist-info/METADATA
Python_PCG-0.2.dist-info/WHEEL
Python_PCG-0.2.dist-info/top_level.txt
Python_PCG-0.2.dist-info/RECORD
