Metadata-Version: 2.1
Name: Python-PCG
Version: 0.2
Summary: Python wrapper around the PCG c++ library.
Author-email: Matthijs Wesseling <matthijs.wesseling@dyme.app>
Project-URL: Homepage, https://github.com/Bladieblah/PyPCG
Project-URL: Bug Tracker, https://github.com/Bladieblah/PyPCG/issues
Classifier: Programming Language :: Python :: 3
Classifier: Operating System :: OS Independent
Classifier: License :: OSI Approved :: MIT License
Requires-Python: >=3.7
License-File: LICENSE
Requires-Dist: numpy (>=1.21.6)
